ingest_data.py
score.py
train.py
housing_assignment2.1_5505-0.1.dist-info/METADATA
housing_assignment2.1_5505-0.1.dist-info/WHEEL
housing_assignment2.1_5505-0.1.dist-info/entry_points.txt
housing_assignment2.1_5505-0.1.dist-info/top_level.txt
housing_assignment2.1_5505-0.1.dist-info/RECORD
