Metadata-Version: 2.1
Name: housing_assignment2.1_5505
Version: 0.1
Summary: Sample code for coding practice
Author-email: Vemuri Harshitha <harshitha.vemuri@tigeranalytics.com>
Project-URL: Homepage, https://github.com/Vemuri-5505/mle-training
Keywords: housing,data training
Classifier: Programming Language :: Python :: 3
Requires-Python: >=3.11
Requires-Dist: numpy
Requires-Dist: pandas
Requires-Dist: scikit-learn
